fontaine/__init__.py
fontaine/_version.py
fontaine/builder.py
fontaine/cmap.py
fontaine/const.py
fontaine/font.py
fontaine/namelist.py
fontaine/charsets/__init__.py
fontaine/charsets/internals/__init__.py
fontaine/charsets/internals/adobe_latin_1.py
fontaine/charsets/internals/adobe_latin_2.py
fontaine/charsets/internals/adobe_latin_3.py
fontaine/charsets/internals/adobe_latin_4.py
fontaine/charsets/internals/adobe_latin_5.py
fontaine/charsets/internals/africaan.py
fontaine/charsets/internals/arabic.py
fontaine/charsets/internals/archaicgreekletter.py
fontaine/charsets/internals/armenian.py
fontaine/charsets/internals/balinese.py
fontaine/charsets/internals/baltic.py
fontaine/charsets/internals/bamum.py
fontaine/charsets/internals/basiccyrillic.py
fontaine/charsets/internals/basicgreek.py
fontaine/charsets/internals/basiclatin.py
fontaine/charsets/internals/batak.py
fontaine/charsets/internals/bengali.py
fontaine/charsets/internals/brahmi.py
fontaine/charsets/internals/buginese.py
fontaine/charsets/internals/canadiansyllabics.py
fontaine/charsets/internals/catalan.py
fontaine/charsets/internals/centraleuropean.py
fontaine/charsets/internals/cham.py
fontaine/charsets/internals/cherokee.py
fontaine/charsets/internals/chesssymbols.py
fontaine/charsets/internals/claudianletters.py
fontaine/charsets/internals/coptic.py
fontaine/charsets/internals/danish-accents.py
fontaine/charsets/internals/danish.py
fontaine/charsets/internals/finnish-accents.py
fontaine/charsets/internals/finnish.py
fontaine/charsets/internals/google_arabic.py
fontaine/charsets/internals/google_cyrillic_historical.py
fontaine/charsets/internals/google_cyrillic_plus.py
fontaine/charsets/internals/google_cyrillic_plus_locl.py
fontaine/charsets/internals/google_cyrillic_pro.py
fontaine/charsets/internals/google_extras.py
fontaine/charsets/internals/google_greek_ancient_musical_symbols.py
fontaine/charsets/internals/google_greek_archaic.py
fontaine/charsets/internals/google_greek_coptic.py
fontaine-1.4.0.dist-info/AUTHORS.txt
fontaine-1.4.0.dist-info/LICENSE.txt
fontaine-1.4.0.dist-info/METADATA
fontaine-1.4.0.dist-info/WHEEL
fontaine-1.4.0.dist-info/top_level.txt
fontaine-1.4.0.dist-info/RECORD
