Metadata-Version: 2.1
Name: fontaine
Version: 1.4.0
Summary: Font analysis tool for determining character/glyph support
Home-page: https://github.com/googlefonts/pyfontaine
Author: Dave Crossland, Felipe Sanches, Vitaly Volkov
Author-email: dave@lab6.com
License: GNU GPLv3
Platform: UNKNOWN
Classifier: Environment :: Console
Classifier: Intended Audience :: Developers
Classifier: License :: OSI Approved :: GNU General Public License v3 (GPLv3)
Classifier: Operating System :: OS Independent
Classifier: Programming Language :: Python :: 3
Classifier: Programming Language :: Python :: 3.6
Classifier: Programming Language :: Python :: 3 :: Only
Requires-Python: >=3.6
Requires-Dist: fonttools
Requires-Dist: lxml
Requires-Dist: PyICU
Requires-Dist: requests
Requires-Dist: tabulate
